iphoto/__init__.py
iphoto/cli.py
iphoto/library.py
iphoto-0.2.2.dist-info/DESCRIPTION.rst
iphoto-0.2.2.dist-info/entry_points.txt
iphoto-0.2.2.dist-info/METADATA
iphoto-0.2.2.dist-info/metadata.json
iphoto-0.2.2.dist-info/RECORD
iphoto-0.2.2.dist-info/top_level.txt
iphoto-0.2.2.dist-info/WHEEL
