Metadata-Version: 2.0
Name: iphoto
Version: 0.2.2
Summary: Command line interface to iPhoto
Home-page: http://www.github.com/staticshock/iphoto.py
Author: Anton Backer
Author-email: olegov@gmail.com
License: ISC
Platform: UNKNOWN
Classifier: Development Status :: 4 - Beta
Classifier: Environment :: Console
Classifier: Intended Audience :: Developers
Classifier: Natural Language :: English
Classifier: License :: OSI Approved :: ISC License (ISCL)
Classifier: Operating System :: POSIX :: Linux
Classifier: Operating System :: MacOS :: MacOS X
Classifier: Operating System :: Microsoft :: Windows
Classifier: Programming Language :: Python
Classifier: Programming Language :: Python :: 3.4
Requires-Dist: sqlalchemy
Requires-Dist: click
